ledger_cli/__init__.py
ledger_cli/excel_exports.py
ledger_cli/ledger.py
ledger_cli/ledger_analyst.py
ledger_cli/ledger_clasic.py
ledger_cli/ledger_export.py
ledger_cli/ledger_grafics.py
ledger_cli/ledger_multifile.py
ledger_cli/ledger_sql.py
ledger_cli/ledger_visual.py
ledger_cli/utils/__init__.py
ledger_cli/utils/calendar.py
ledger_cli/utils/order.py
ledger_cli_toolkit-1.8.6.dist-info/licenses/LICENSE
ledger_cli_toolkit-1.8.6.dist-info/METADATA
ledger_cli_toolkit-1.8.6.dist-info/WHEEL
ledger_cli_toolkit-1.8.6.dist-info/entry_points.txt
ledger_cli_toolkit-1.8.6.dist-info/top_level.txt
ledger_cli_toolkit-1.8.6.dist-info/RECORD
