Metadata-Version: 2.4
Name: ledger-cli-toolkit
Version: 1.8.6
Summary: Library for manipulating accounting files in .ledger format.
Home-page: https://github.com/EddyBel/Ledgerpy
Author: Eduardo Rangel
Author-email: dante61918@gmail.com
License: MIT
Project-URL: Bug Tracker, https://github.com/EddyBel/Ledgerpy/issues
Classifier: Programming Language :: Python :: 3
Classifier: License :: OSI Approved :: MIT License
Classifier: Operating System :: OS Independent
Classifier: Development Status :: 4 - Beta
Classifier: Intended Audience :: Developers
Classifier: Topic :: Office/Business :: Financial :: Accounting
Requires-Python: >=3.7
License-File: LICENSE
Requires-Dist: tabulate>=0.9.0
Provides-Extra: dev
Requires-Dist: pytest>=7.0; extra == "dev"
Requires-Dist: black; extra == "dev"
Requires-Dist: flake8; extra == "dev"
Dynamic: author
Dynamic: author-email
Dynamic: classifier
Dynamic: description
Dynamic: description-content-type
Dynamic: home-page
Dynamic: license
Dynamic: license-file
Dynamic: project-url
Dynamic: provides-extra
Dynamic: requires-dist
Dynamic: requires-python
Dynamic: summary
